core/__init__.py
core/app_operations.py
core/file_operations.py
CustomWindowsCLILang-2.3.0.dist-info/LICENSE
CustomWindowsCLILang-2.3.0.dist-info/METADATA
CustomWindowsCLILang-2.3.0.dist-info/WHEEL
CustomWindowsCLILang-2.3.0.dist-info/entry_points.txt
CustomWindowsCLILang-2.3.0.dist-info/top_level.txt
CustomWindowsCLILang-2.3.0.dist-info/RECORD
