Metadata-Version: 2.1
Name: CustomWindowsCLILang
Version: 2.3.0
Summary: A custom CLI language for handling Windows tasks
Author: vinit
Author-email: vineetp6@gmail.com
Classifier: Programming Language :: Python :: 3
Classifier: Operating System :: Microsoft :: Windows
Requires-Python: >=3.7
License-File: LICENSE
